SERobESP/__init__.py
serobesp-0.1.2.dist-info/licenses/LICENSE
serobesp-0.1.2.dist-info/METADATA
serobesp-0.1.2.dist-info/WHEEL
serobesp-0.1.2.dist-info/top_level.txt
serobesp-0.1.2.dist-info/RECORD
