Metadata-Version: 2.4
Name: SERobESP
Version: 0.1.2
Summary: Control ESP32-based robot kits via serial or Wi-Fi
Home-page: https://github.com/S001T/SERobESP.git
Author: Sarkis Tamaryan
Author-email: Sarkis Tamaryan <you@example.com>
License: MIT
Project-URL: Homepage, https://github.com/S001T/SERobESP
Classifier: Programming Language :: Python :: 3
Classifier: License :: OSI Approved :: MIT License
Classifier: Operating System :: OS Independent
Requires-Python: >=3.7
License-File: LICENSE
Dynamic: author
Dynamic: home-page
Dynamic: license-file
Dynamic: requires-python
